{
  "hash": "c7f353b7",
  "configHash": "abeba376",
  "lockfileHash": "a52ce195",
  "browserHash": "2e28fd95",
  "optimized": {
    "vue": {
      "src": "../../../../node_modules/vue/dist/vue.runtime.esm-bundler.js",
      "file": "vue.js",
      "fileHash": "5dc9e786",
      "needsInterop": false
    },
    "vitepress > @vue/devtools-api": {
      "src": "../../../../node_modules/@vue/devtools-api/dist/index.js",
      "file": "vitepress___@vue_devtools-api.js",
      "fileHash": "6b31d717",
      "needsInterop": false
    },
    "vitepress > @vueuse/core": {
      "src": "../../../../node_modules/@vueuse/core/index.mjs",
      "file": "vitepress___@vueuse_core.js",
      "fileHash": "d71c1f16",
      "needsInterop": false
    },
    "@theme/index": {
      "src": "../../../../node_modules/vitepress/dist/client/theme-default/index.js",
      "file": "@theme_index.js",
      "fileHash": "60d60223",
      "needsInterop": false
    }
  },
  "chunks": {
    "chunk-QBQC6V45": {
      "file": "chunk-QBQC6V45.js"
    },
    "chunk-EKBJ2FPM": {
      "file": "chunk-EKBJ2FPM.js"
    }
  }
}